baseball/__init__.py
baseball/baseball.py
baseball/baseball_events.py
baseball/fetch_game.py
baseball/generate_svg.py
baseball/process_game_json.py
baseball/process_game_xml.py
baseball/stats.py
baseball-17.60.dist-info/LICENSE
baseball-17.60.dist-info/METADATA
baseball-17.60.dist-info/WHEEL
baseball-17.60.dist-info/top_level.txt
baseball-17.60.dist-info/RECORD
