Metadata-Version: 2.1
Name: baseball
Version: 17.60
Summary: Library to download, anaylyze, and visualize events in Major League Baseball games.
Home-page: https://github.com/benjamincrom/baseball
Author: Benjamin B. Crom
Author-email: benjamincrom@gmail.com
License: MIT
License-File: LICENSE
Requires-Dist: python-dateutil
Requires-Dist: pytz
Requires-Dist: requests
